teedoc_plugin_theme_default/__init__.py
teedoc_plugin_theme_default/trans_finish.py
teedoc_plugin_theme_default/trans_prepare.py
teedoc_plugin_theme_default/version.py
teedoc_plugin_theme_default/assets/anchor.svg
teedoc_plugin_theme_default/assets/array.svg
teedoc_plugin_theme_default/assets/back.svg
teedoc_plugin_theme_default/assets/dark.css
teedoc_plugin_theme_default/assets/dark_mode.svg
teedoc_plugin_theme_default/assets/ext_link.svg
teedoc_plugin_theme_default/assets/indicator.svg
teedoc_plugin_theme_default/assets/jquery.min.js
teedoc_plugin_theme_default/assets/light.css
teedoc_plugin_theme_default/assets/light_mode.svg
teedoc_plugin_theme_default/assets/main.js
teedoc_plugin_theme_default/assets/menu.svg
teedoc_plugin_theme_default/assets/pre_main.js
teedoc_plugin_theme_default/assets/print.svg
teedoc_plugin_theme_default/assets/prism.min.css
teedoc_plugin_theme_default/assets/prism.min.js
teedoc_plugin_theme_default/assets/split.js
teedoc_plugin_theme_default/assets/to-top.svg
teedoc_plugin_theme_default/assets/tocbot.min.js
teedoc_plugin_theme_default/assets/viewer.min.css
teedoc_plugin_theme_default/assets/viewer.min.js
teedoc_plugin_theme_default/locales/messages.pot
teedoc_plugin_theme_default/locales/ja/LC_MESSAGES/messages.mo
teedoc_plugin_theme_default/locales/ja/LC_MESSAGES/messages.po
teedoc_plugin_theme_default/locales/zh_CN/LC_MESSAGES/messages.mo
teedoc_plugin_theme_default/locales/zh_CN/LC_MESSAGES/messages.po
teedoc_plugin_theme_default/locales/zh_TW/LC_MESSAGES/messages.mo
teedoc_plugin_theme_default/locales/zh_TW/LC_MESSAGES/messages.po
teedoc_plugin_theme_default/templates/404.html
teedoc_plugin_theme_default/templates/article.html
teedoc_plugin_theme_default/templates/page.html
teedoc_plugin_theme_default/templates/page_base.html
teedoc_plugin_theme_default/templates/redirect.html
teedoc_plugin_theme_default-1.25.0.dist-info/LICENSE
teedoc_plugin_theme_default-1.25.0.dist-info/METADATA
teedoc_plugin_theme_default-1.25.0.dist-info/WHEEL
teedoc_plugin_theme_default-1.25.0.dist-info/top_level.txt
teedoc_plugin_theme_default-1.25.0.dist-info/RECORD
